ghstats.py
github_api.py
heatmap.py
render.py
utils.py
gh_stats_heatmap-1.0.3.dist-info/licenses/LICENSE
plugins/__init__.py
plugins/base.py
plugins/global_leaderboard.py
gh_stats_heatmap-1.0.3.dist-info/METADATA
gh_stats_heatmap-1.0.3.dist-info/WHEEL
gh_stats_heatmap-1.0.3.dist-info/entry_points.txt
gh_stats_heatmap-1.0.3.dist-info/top_level.txt
gh_stats_heatmap-1.0.3.dist-info/RECORD
