Metadata-Version: 2.4
Name: gh-stats-heatmap
Version: 1.0.3
Summary: GitHub Contribution Graph in your terminal — for hackers who prefer Unicode over UI
Home-page: https://github.com/Gizmet/gh-stats-heatmap
Author: Gizmet
Author-email: Gizmet <gizmet@example.com>
Maintainer-email: Gizmet <gizmet@example.com>
License: MIT
Project-URL: Homepage, https://github.com/Gizmet/github-contribution-heatmap-viewer
Project-URL: Documentation, https://github.com/Gizmet/github-contribution-heatmap-viewer#readme
Project-URL: Repository, https://github.com/Gizmet/github-contribution-heatmap-viewer
Project-URL: Bug Tracker, https://github.com/Gizmet/github-contribution-heatmap-viewer/issues
Keywords: github,terminal,heatmap,contributions,cli,rich
Classifier: Development Status :: 4 - Beta
Classifier: Intended Audience :: Developers
Classifier: License :: OSI Approved :: MIT License
Classifier: Operating System :: OS Independent
Classifier: Programming Language :: Python :: 3
Classifier: Programming Language :: Python :: 3.9
Classifier: Programming Language :: Python :: 3.10
Classifier: Programming Language :: Python :: 3.11
Classifier: Programming Language :: Python :: 3.12
Classifier: Topic :: Software Development :: Libraries :: Python Modules
Classifier: Topic :: Terminals
Classifier: Topic :: Utilities
Requires-Python: >=3.9
License-File: LICENSE
Requires-Dist: requests>=2.25.0
Requires-Dist: rich>=10.0.0
Requires-Dist: typer>=0.4.0
Provides-Extra: dev
Requires-Dist: pytest>=6.0; extra == "dev"
Requires-Dist: black>=21.0; extra == "dev"
Requires-Dist: flake8>=3.8; extra == "dev"
Dynamic: author
Dynamic: home-page
Dynamic: license-file
Dynamic: requires-python
